colmet/__init__.py
colmet/collector/__init__.py
colmet/collector/elasticsearch.py
colmet/collector/hdf5.py
colmet/collector/main.py
colmet/common/__init__.py
colmet/common/exceptions.py
colmet/common/job.py
colmet/common/utils.py
colmet/common/backends/__init__.py
colmet/common/backends/base.py
colmet/common/backends/zeromq.py
colmet/common/metrics/RAPLstats.py
colmet/common/metrics/__init__.py
colmet/common/metrics/base.py
colmet/common/metrics/infinibandstats.py
colmet/common/metrics/ipmipowerstats.py
colmet/common/metrics/jobprocstats.py
colmet/common/metrics/lustrestats.py
colmet/common/metrics/nvidiastats.py
colmet/common/metrics/perfhwstats.py
colmet/common/metrics/procstats.py
colmet/common/metrics/taskstats.py
colmet/common/metrics/temperaturestats.py
colmet/node/__init__.py
colmet/node/main.py
colmet/node/backends/RAPLstats.py
colmet/node/backends/__init__.py
colmet/node/backends/infinibandstats.py
colmet/node/backends/ipmipowerstats.py
colmet/node/backends/jobprocstats.py
colmet/node/backends/lustrestats.py
colmet/node/backends/nvidiastats.py
colmet/node/backends/perfhwstats.py
colmet/node/backends/procstats.py
colmet/node/backends/taskstats.py
colmet/node/backends/temperaturestats.py
colmet/node/backends/genetlink/__init__.py
colmet/node/backends/genetlink/genetlink.py
colmet/node/backends/genetlink/netlink.py
tests/__init__.py
tests/test_metrics_base.py
tests/test_metrics_procstats.py
tests/test_metrics_taskstats.py
colmet-0.6.10.dist-info/LICENSE
colmet-0.6.10.dist-info/METADATA
colmet-0.6.10.dist-info/WHEEL
colmet-0.6.10.dist-info/entry_points.txt
colmet-0.6.10.dist-info/top_level.txt
colmet-0.6.10.dist-info/RECORD
