Metadata-Version: 2.1
Name: colmet
Version: 0.6.10
Summary: A utility to monitor the jobs ressources in a HPC environment, espacially OAR
Home-page: http://oar.imag.fr/
Author: Philippe Le Brouster, Olivier Richard
Author-email: philippe.le-brouster@imag.fr, olivier.richard@imag.fr
Maintainer: Salem Harrache
Maintainer-email: salem.harrache@inria.fr
License: GNU GPL
Keywords: monitoring,taskstat,oar,hpc,sciences
Platform: Linux
Classifier: Development Status :: 4 - Beta
Classifier: Environment :: Console
Classifier: Intended Audience :: System Administrators
Classifier: License :: OSI Approved :: GNU General Public License (GPL)
Classifier: Operating System :: OS Independent
Classifier: Programming Language :: Python
Classifier: Topic :: Software Development :: Libraries :: Python Modules
Classifier: Topic :: System :: Monitoring
Classifier: Topic :: System :: Clustering
Classifier: Programming Language :: Python :: 3.5
License-File: LICENSE
Requires-Dist: tables
Requires-Dist: pyinotify
Requires-Dist: pyzmq
Requires-Dist: requests
